battlebots/__init__.py
battlebots/__main__.py
battlebots/art_to_gif.py
battlebots/cli.py
battlebots-1.0.0.dist-info/METADATA
battlebots-1.0.0.dist-info/WHEEL
battlebots-1.0.0.dist-info/entry_points.txt
battlebots-1.0.0.dist-info/top_level.txt
battlebots-1.0.0.dist-info/RECORD
