Metadata-Version: 2.1
Name: battlebots
Version: 1.0.0
Summary: BagelCon Battlebots Runner
Home-page: https://github.com/TylerLubeck/battlebots
Author: Tyler Lubeck
Author-email: tyler@tylerlubeck.com
License: UNKNOWN
Platform: UNKNOWN
Requires-Python: >=3.8,<4.0
Requires-Dist: colorama (<=0.5.0,>=0.4.3)
Requires-Dist: docker (<5.0.0,>=4.2.2)
Requires-Dist: typer (<0.4.0,>=0.3.1)
Requires-Dist: pillow (>=7.2.0<8.0.0)
